{
	"info": {
		"_postman_id": "051b95de-b201-489d-b4c8-69bcbd13ffdd",
		"name": "Music_Library_API",
		"schema": "https://schema.getpostman.com/json/collection/v2.1.0/collection.json"
	},
	"item": [
		{
			"name": "Get_All_Songs",
			"request": {
				"method": "GET",
				"header": [],
				"url": {
					"raw": "http://127.0.0.1:8000/music/",
					"protocol": "http",
					"host": [
						"127",
						"0",
						"0",
						"1"
					],
					"port": "8000",
					"path": [
						"music",
						""
					]
				}
			},
			"response": []
		},
		{
			"name": "Create_Song",
			"request": {
				"method": "POST",
				"header": [],
				"body": {
					"mode": "raw",
					"raw": "{\r\n    \"title\": \"Down Below\",\r\n    \"artist\": \"Roddy Rich\",\r\n    \"album\": \"Feed Tha Streets 2\",\r\n    \"release_date\": \"2018-02-28T00:00:00Z\"\r\n}",
					"options": {
						"raw": {
							"language": "json"
						}
					}
				},
				"url": {
					"raw": "http://127.0.0.1:8000/music/",
					"protocol": "http",
					"host": [
						"127",
						"0",
						"0",
						"1"
					],
					"port": "8000",
					"path": [
						"music",
						""
					]
				}
			},
			"response": []
		},
		{
			"name": "Get_Song",
			"request": {
				"method": "GET",
				"header": [],
				"url": {
					"raw": "http://127.0.0.1:8000/music/5",
					"protocol": "http",
					"host": [
						"127",
						"0",
						"0",
						"1"
					],
					"port": "8000",
					"path": [
						"music",
						"5"
					]
				}
			},
			"response": []
		},
		{
			"name": "update_song",
			"request": {
				"method": "PUT",
				"header": [],
				"body": {
					"mode": "raw",
					"raw": "{\r\n    \"id\": 7,\r\n    \"title\": \"Down Below 2\",\r\n    \"artist\": \"Roddy Rich\",\r\n    \"album\": \"Feed Tha Streets 2\",\r\n    \"release_date\": \"2018-02-28T00:00:00Z\",\r\n    \"do_you_like_the_song\": true\r\n}",
					"options": {
						"raw": {
							"language": "json"
						}
					}
				},
				"url": {
					"raw": "http://127.0.0.1:8000/music/7/",
					"protocol": "http",
					"host": [
						"127",
						"0",
						"0",
						"1"
					],
					"port": "8000",
					"path": [
						"music",
						"7",
						""
					]
				}
			},
			"response": []
		},
		{
			"name": "delete_song",
			"request": {
				"method": "DELETE",
				"header": [],
				"url": {
					"raw": "http://127.0.0.1:8000/music/4/",
					"protocol": "http",
					"host": [
						"127",
						"0",
						"0",
						"1"
					],
					"port": "8000",
					"path": [
						"music",
						"4",
						""
					]
				}
			},
			"response": []
		}
	]
}